[
 {
  "title": "NPRMs (Connected to Final Rules)",
  "supplementary_content": [
   {
    "title": "Medicaid Program; Eligibility Changes Under the Affordable Care Act of 2010, August 17, 2011 (76 FR 51148)",
    "url": "https://www.federalregister.gov/documents/2011/08/17/2011-20756/medicaid-program-eligibility-changes-under-the-affordable-care-act-of-2010",
    "sections": [
     {
      "title": "42",
      "part": "436",
      "section": "4"
     },
     {
      "title": "42",
      "part": "436",
      "section": "110"
     },
     {
      "title": "42",
      "part": "436",
      "section": "116"
     },
     {
      "title": "42",
      "part": "436",
      "section": "118"
     },
     {
      "title": "42",
      "part": "436",
      "section": "119"
     },
     {
      "title": "42",
      "part": "436",
      "section": "218"
     },
     {
      "title": "42",
      "part": "436",
      "section": "403"
     },
     {
      "title": "42",
      "part": "436",
      "section": "603"
     },
     {
      "title": "42",
      "part": "436",
      "section": "905"
     },
     {
      "title": "42",
      "part": "436",
      "section": "907"
     },
     {
      "title": "42",
      "part": "436",
      "section": "908"
     },
     {
      "title": "42",
      "part": "436",
      "section": "911"
     },
     {
      "title": "42",
      "part": "436",
      "section": "916"
     },
     {
      "title": "42",
      "part": "436",
      "section": "94"
     },
     {
      "title": "42",
      "part": "436",
      "section": "945"
     },
     {
      "title": "42",
      "part": "436",
      "section": "949"
     },
     {
      "title": "42",
      "part": "436",
      "section": "952"
     },
     {
      "title": "42",
      "part": "436",
      "section": "956"
     },
     {
      "title": "42",
      "part": "436",
      "section": "1200"
     }
    ]
   }
  ]
 },
 {
  "title": "Technical Assistance for States",
  "supplementary_content": [
   {
    "title": "Streamlined Eligibility and Enrollment for Non-MAGI Populations, June 22, 2015",
    "url": "https://www.medicaid.gov/state-resource-center/mac-learning-collaboratives/downloads/non-magi-populations.pdf",
    "sections": [
     {
      "title": "42",
      "part": "436",
      "section": "404"
     },
     {
      "title": "42",
      "part": "436",
      "section": "603"
     },
     {
      "title": "42",
      "part": "436",
      "section": "907"
     },
     {
      "title": "42",
      "part": "436",
      "section": "908"
     },
     {
      "title": "42",
      "part": "436",
      "section": "911"
     },
     {
      "title": "42",
      "part": "436",
      "section": "912"
     },
     {
      "title": "42",
      "part": "436",
      "section": "916"
     },
     {
      "title": "42",
      "part": "436",
      "section": "945"
     },
     {
      "title": "42",
      "part": "436",
      "section": "948"
     },
     {
      "title": "42",
      "part": "436",
      "section": "949"
     },
     {
      "title": "42",
      "part": "436",
      "section": "952"
     },
     {
      "title": "42",
      "part": "436",
      "section": "956"
     }
    ]
   },
   {
    "title": "Application, Verification and Renewals, April 19, 2012 ",
    "url": "https://www.medicaid.gov/state-resource-center/downloads/4-19-12-application-verification-renewals-slides.pdf",
    "sections": [
     {
      "title": "42",
      "part": "436",
      "section": "907"
     },
     {
      "title": "42",
      "part": "436",
      "section": "910"
     },
     {
      "title": "42",
      "part": "436",
      "section": "916"
     },
     {
      "title": "42",
      "part": "436",
      "section": "945"
     },
     {
      "title": "42",
      "part": "436",
      "section": "945"
     },
     {
      "title": "42",
      "part": "436",
      "section": "948"
     },
     {
      "title": "42",
      "part": "436",
      "section": "949"
     },
     {
      "title": "42",
      "part": "436",
      "section": "952"
     },
     {
      "title": "42",
      "part": "436",
      "section": "956"
     },
     {
      "title": "42",
      "part": "436",
      "section": "96"
     }
    ]
   },
   {
    "title": "Application, Verification and Renewals, April 19, 2012 ",
    "url": "https://www.medicaid.gov/state-resource-center/downloads/4-19-12-application-verification-renewals-slides.pdf",
    "sections": [
     {
      "title": "42",
      "part": "436",
      "section": "907"
     },
     {
      "title": "42",
      "part": "436",
      "section": "910"
     },
     {
      "title": "42",
      "part": "436",
      "section": "916"
     },
     {
      "title": "42",
      "part": "436",
      "section": "945"
     },
     {
      "title": "42",
      "part": "436",
      "section": "945"
     },
     {
      "title": "42",
      "part": "436",
      "section": "948"
     },
     {
      "title": "42",
      "part": "436",
      "section": "949"
     },
     {
      "title": "42",
      "part": "436",
      "section": "952"
     },
     {
      "title": "42",
      "part": "436",
      "section": "956"
     },
     {
      "title": "42",
      "part": "436",
      "section": "96"
     }
    ]
   }
  ]
 }
]